README.rst
setup.py
datacoco_redis_tools/__init__.py
datacoco_redis_tools/redis_tools.py
datacoco_redis_tools.egg-info/PKG-INFO
datacoco_redis_tools.egg-info/SOURCES.txt
datacoco_redis_tools.egg-info/dependency_links.txt
datacoco_redis_tools.egg-info/requires.txt
datacoco_redis_tools.egg-info/top_level.txt