Metadata-Version: 1.0
Name: datacoco-redis-tools
Version: 0.1.1
Summary: Data common code for Redis by Equinox
Home-page: https://github.com/equinoxfitness/datacoco-redis_tools
Author: Equinox
Author-email: UNKNOWN
License: MIT
Keywords: helper,db,common
Platform: UNKNOWN
